token_data/__init__.py
token_data/_modidx.py
token_data/coinbase.py
token_data/hyper_account.py
token_data/hyperliquid.py
token_data-0.0.4.dist-info/licenses/LICENSE
token_data-0.0.4.dist-info/METADATA
token_data-0.0.4.dist-info/WHEEL
token_data-0.0.4.dist-info/entry_points.txt
token_data-0.0.4.dist-info/top_level.txt
token_data-0.0.4.dist-info/RECORD
